mcp_server_undetected_chromedriver/__init__.py
mcp_server_undetected_chromedriver/server.py
iflow_mcp_mcp_undetected_chromedriver-0.1.1.dist-info/METADATA
iflow_mcp_mcp_undetected_chromedriver-0.1.1.dist-info/WHEEL
iflow_mcp_mcp_undetected_chromedriver-0.1.1.dist-info/entry_points.txt
iflow_mcp_mcp_undetected_chromedriver-0.1.1.dist-info/licenses/LICENSE
iflow_mcp_mcp_undetected_chromedriver-0.1.1.dist-info/RECORD
