Metadata-Version: 2.4
Name: iflow-mcp_mcp-undetected-chromedriver
Version: 0.1.1
Summary: Add your description here
License: MIT
License-File: LICENSE
Requires-Python: >=3.11
Requires-Dist: mcp[cli]>=1.6.0
Requires-Dist: setuptools>=65.0.0
Requires-Dist: undetected-chromedriver>=3.5.5
Requires-Dist: webdriver-manager>=4.0.2
